<?xml version="1.0" encoding="UTF-8" standalone="no"?><!--This data builds a LotGraph, to be used with the BotLotDS object. https://github.com/GregJohnStewart/BotLot --><root><node id="BOTLOTNODE19212231111085586864" name="node0" numEdges="1"><edge endNode="BOTLOTNODE20408307692119927707" id="BOTLOTEDGE06876559331519432458" metric="5.0"/></node><node id="BOTLOTNODE20408307692119927707" name="node1" numEdges="2"><edge endNode="BOTLOTNODE04100026960221189882" id="BOTLOTEDGE17502365821886527066" metric="9.0"/><edge endNode="BOTLOTNODE20408307692119927707" id="BOTLOTEDGE10377772441846073402" metric="10.0"/></node><node id="BOTLOTNODE04100026960221189882" name="node2" numEdges="4"><edge endNode="BOTLOTNODE21296639361441517998" id="BOTLOTEDGE16831351550637636871" metric="2.0"/><edge endNode="BOTLOTNODE20408307692119927707" id="BOTLOTEDGE01347491120243388334" metric="9.0"/><edge endNode="BOTLOTNODE00919499761861557591" id="BOTLOTEDGE03252170401235713684" metric="1.0"/><edge endNode="BOTLOTNODE02053394150354559132" id="BOTLOTEDGE18892650741131940574" metric="6.0"/></node><node id="BOTLOTNODE21296639361441517998" name="node3" numEdges="3"><edge endNode="BOTLOTNODE12807379300684775619" id="BOTLOTEDGE05751439941670364379" metric="6.0"/><edge endNode="BOTLOTNODE04100026960221189882" id="BOTLOTEDGE00604217500131315093" metric="2.0"/><edge endNode="BOTLOTNODE11001673021661818345" id="BOTLOTEDGE05380743572130412388" metric="5.0"/></node><node id="BOTLOTNODE12807379300684775619" name="node4" numEdges="1"><edge endNode="BOTLOTNODE08007420291869188270" id="BOTLOTEDGE01434870220847994121" metric="9.0"/></node><node id="BOTLOTNODE08007420291869188270" name="node5" numEdges="1"><edge endNode="BOTLOTNODE10342772291052268208" id="BOTLOTEDGE17747368440359704212" metric="3.0"/></node><node id="BOTLOTNODE00919499761861557591" name="node6" numEdges="1"><edge endNode="BOTLOTNODE20067247422030513283" id="BOTLOTEDGE00645600541661370693" metric="1.0"/></node><node id="BOTLOTNODE20067247422030513283" name="node7" numEdges="2"><edge endNode="BOTLOTNODE21296639361441517998" id="BOTLOTEDGE11780462841125471804" metric="2.0"/><edge endNode="BOTLOTNODE02816622002144144692" id="BOTLOTEDGE02526527562022124628" metric="2.0"/></node><node id="BOTLOTNODE10342772291052268208" name="node8" numEdges="1"><edge endNode="BOTLOTNODE12807379300684775619" id="BOTLOTEDGE19072935000925224614" metric="6.0"/></node><node id="BOTLOTNODE02816622002144144692" name="node9" numEdges="1"><edge endNode="BOTLOTNODE07637658542055222265" id="BOTLOTEDGE15802536280993662138" metric="4.0"/></node><node id="BOTLOTNODE07637658542055222265" name="node10" numEdges="1"><edge endNode="BOTLOTNODE10342772291052268208" id="BOTLOTEDGE11074045711905255632" metric="6.0"/></node><node id="BOTLOTNODE11001673021661818345" name="node11" numEdges="1"><edge endNode="BOTLOTNODE21296639361441517998" id="BOTLOTEDGE00301286401885173063" metric="5.0"/></node><node id="BOTLOTNODE02053394150354559132" name="node12" numEdges="1"><edge endNode="BOTLOTNODE20056154140739164826" id="BOTLOTEDGE06613516420449019080" metric="8.0"/></node><node id="BOTLOTNODE20056154140739164826" name="node13" numEdges="0"/></root>